{
	"groups":[
		{
			"keys":"home-bg_jpg,home-rule_png,home-prize_png,home-rule-btn_png,home-start-btn_png,home-tip_png,level1_png,level2_png,level3_png,home-title_png,home-arrow_png,home-gray_png,home-red_png,home-lv-bg_jpg,home-sorry_png,db-casino-bg_png,db-grass_png,db-jixu_png",
			"name":"preload"
		},
		{
			"keys":"",
			"name":"loading"
		},
		{
			"keys":"db-mask0_png,db-mask2_png,db-mask4_png,db-mask6_png,db-mask8_png,db-more-coin_png,db-play_jpg,db-thanku-b_png,db-thanku-y_png,db-title_png,db-20coins_png,db-chou_png,db-click_png,db-coins_png,db-grass_png,db-item0_png,db-item0-b_png,db-item0-y_png,db-item2_png,db-item2-b_png,db-item2-y_png,db-item4_png,db-item4-b_png,db-item4-y_png,db-item6_png,db-item6-b_png,db-item6-y_png,db-item8_png,db-item8-b_png,db-item8-y_png,db-item-thanku_png,debao-welcome_png,debao-tree_png,db-lose_png,db-won_png,db-add-chart_png,db-item2s_png,db-item4s_png,db-item6s_png,db-item8s_png,db-item0s_png,db-finish_png,db-goods-save_png,tmall_png,db-coupon-pop_png,db-goods_png,db-goods-bg_jpg,db-goods-saved_png",
			"name":"debao"
		},
		{
			"keys":"zb-title_png,zb-borad_jpg,zb-color-bg0_png,zb-color-bg1_png,zb-lock_png,zb-lock-bg_png,zb-pick-bg_jpg,zb-color-tip_png,zb-meng4c_png,zb-meng4g_png,zb-meng1c_png,zb-meng1g_png,zb-meng2c_png,zb-meng2g_png,zb-meng3c_png,zb-meng3g_png,zb-finish-pop_png,zb-pingtu-bg_jpg,zb-pingtu-jia_png,zb-pingtu-click_png,zb-pingtu-next_png,zb-pingtu-over_png,zb-pingtu-save_png",
			"name":"zb"
		},
		{
			"keys":"wk-bian-hand_png,wk-bian-tip_png,wk-6_jpg,wk-53_png,wk-52_png,wk-51_png,wk-4_jpg,wk-341_png,wk-340_png,wk-33_png,wk-32_png,wk-31_png,wk-23_png,wk-22_png,wk-21_png,wk-1_jpg,wk-1next_png,wk-chart_png",
			"name":"wk"
		}
	],
	"resources":[
		{
			"name":"home-bg_jpg",
			"type":"image",
			"url":"home/home-bg.jpg"
		},
		{
			"name":"home-rule_png",
			"type":"image",
			"url":"home/home-rule.png"
		},
		{
			"name":"home-prize_png",
			"type":"image",
			"url":"home/home-prize.png"
		},
		{
			"name":"home-rule-btn_png",
			"type":"image",
			"url":"home/home-rule-btn.png"
		},
		{
			"name":"home-start-btn_png",
			"type":"image",
			"url":"home/home-start-btn.png"
		},
		{
			"name":"home-tip_png",
			"type":"image",
			"url":"home/home-tip.png"
		},
		{
			"name":"level1_png",
			"type":"image",
			"url":"home/level1.png"
		},
		{
			"name":"level2_png",
			"type":"image",
			"url":"home/level2.png"
		},
		{
			"name":"level3_png",
			"type":"image",
			"url":"home/level3.png"
		},
		{
			"name":"home-title_png",
			"type":"image",
			"url":"home/home-title.png"
		},
		{
			"name":"home-arrow_png",
			"type":"image",
			"url":"home/home-arrow.png"
		},
		{
			"name":"home-gray_png",
			"type":"image",
			"url":"home/home-gray.png"
		},
		{
			"name":"home-red_png",
			"type":"image",
			"url":"home/home-red.png"
		},
		{
			"name":"home-lv-bg_jpg",
			"type":"image",
			"url":"home/home-lv-bg.jpg"
		},
		{
			"name":"home-sorry_png",
			"type":"image",
			"url":"home/home-sorry.png"
		},
		{
			"name":"db-mask0_png",
			"type":"image",
			"url":"debao/db-mask0.png"
		},
		{
			"name":"db-mask2_png",
			"type":"image",
			"url":"debao/db-mask2.png"
		},
		{
			"name":"db-mask4_png",
			"type":"image",
			"url":"debao/db-mask4.png"
		},
		{
			"name":"db-mask6_png",
			"type":"image",
			"url":"debao/db-mask6.png"
		},
		{
			"name":"db-mask8_png",
			"type":"image",
			"url":"debao/db-mask8.png"
		},
		{
			"name":"db-more-coin_png",
			"type":"image",
			"url":"debao/db-more-coin.png"
		},
		{
			"name":"db-play_jpg",
			"type":"image",
			"url":"debao/db-play.jpg"
		},
		{
			"name":"db-thanku-b_png",
			"type":"image",
			"url":"debao/db-thanku-b.png"
		},
		{
			"name":"db-thanku-y_png",
			"type":"image",
			"url":"debao/db-thanku-y.png"
		},
		{
			"name":"db-title_png",
			"type":"image",
			"url":"debao/db-title.png"
		},
		{
			"name":"db-20coins_png",
			"type":"image",
			"url":"debao/db-20coins.png"
		},
		{
			"name":"db-chou_png",
			"type":"image",
			"url":"debao/db-chou.png"
		},
		{
			"name":"db-click_png",
			"type":"image",
			"url":"debao/db-click.png"
		},
		{
			"name":"db-coins_png",
			"type":"image",
			"url":"debao/db-coins.png"
		},
		{
			"name":"db-grass_png",
			"type":"image",
			"url":"debao/db-grass.png"
		},
		{
			"name":"db-item0_png",
			"type":"image",
			"url":"debao/db-item0.png"
		},
		{
			"name":"db-item0-b_png",
			"type":"image",
			"url":"debao/db-item0-b.png"
		},
		{
			"name":"db-item0-y_png",
			"type":"image",
			"url":"debao/db-item0-y.png"
		},
		{
			"name":"db-item2_png",
			"type":"image",
			"url":"debao/db-item2.png"
		},
		{
			"name":"db-item2-b_png",
			"type":"image",
			"url":"debao/db-item2-b.png"
		},
		{
			"name":"db-item2-y_png",
			"type":"image",
			"url":"debao/db-item2-y.png"
		},
		{
			"name":"db-item4_png",
			"type":"image",
			"url":"debao/db-item4.png"
		},
		{
			"name":"db-item4-b_png",
			"type":"image",
			"url":"debao/db-item4-b.png"
		},
		{
			"name":"db-item4-y_png",
			"type":"image",
			"url":"debao/db-item4-y.png"
		},
		{
			"name":"db-item6_png",
			"type":"image",
			"url":"debao/db-item6.png"
		},
		{
			"name":"db-item6-b_png",
			"type":"image",
			"url":"debao/db-item6-b.png"
		},
		{
			"name":"db-item6-y_png",
			"type":"image",
			"url":"debao/db-item6-y.png"
		},
		{
			"name":"db-item8_png",
			"type":"image",
			"url":"debao/db-item8.png"
		},
		{
			"name":"db-item8-b_png",
			"type":"image",
			"url":"debao/db-item8-b.png"
		},
		{
			"name":"db-item8-y_png",
			"type":"image",
			"url":"debao/db-item8-y.png"
		},
		{
			"name":"db-item-thanku_png",
			"type":"image",
			"url":"debao/db-item-thanku.png"
		},
		{
			"name":"debao-welcome_png",
			"type":"image",
			"url":"debao/debao-welcome.png"
		},
		{
			"name":"debao-tree_png",
			"type":"image",
			"url":"debao/debao-tree.png"
		},
		{
			"name":"db-lose_png",
			"type":"image",
			"url":"debao/db-lose.png"
		},
		{
			"name":"db-won_png",
			"type":"image",
			"url":"debao/db-won.png"
		},
		{
			"name":"db-add-chart_png",
			"type":"image",
			"url":"debao/db-add-chart.png"
		},
		{
			"name":"db-casino-bg_png",
			"type":"image",
			"url":"debao/db-casino-bg.png"
		},
		{
			"name":"db-jixu_png",
			"type":"image",
			"url":"debao/db-jixu.png"
		},
		{
			"name":"db-item2s_png",
			"type":"image",
			"url":"debao/db-item2s.png"
		},
		{
			"name":"db-item4s_png",
			"type":"image",
			"url":"debao/db-item4s.png"
		},
		{
			"name":"db-item6s_png",
			"type":"image",
			"url":"debao/db-item6s.png"
		},
		{
			"name":"db-item8s_png",
			"type":"image",
			"url":"debao/db-item8s.png"
		},
		{
			"name":"db-item0s_png",
			"type":"image",
			"url":"debao/db-item0s.png"
		},
		{
			"name":"db-finish_png",
			"type":"image",
			"url":"debao/db-finish.png"
		},
		{
			"name":"db-goods-save_png",
			"type":"image",
			"url":"debao/db-goods-save.png"
		},
		{
			"name":"tmall_png",
			"type":"image",
			"url":"debao/tmall.png"
		},
		{
			"name":"db-coupon-pop_png",
			"type":"image",
			"url":"debao/db-coupon-pop.png"
		},
		{
			"name":"db-goods_png",
			"type":"image",
			"url":"debao/db-goods.png"
		},
		{
			"name":"db-goods-bg_jpg",
			"type":"image",
			"url":"debao/db-goods-bg.jpg"
		},
		{
			"name":"db-goods-saved_png",
			"type":"image",
			"url":"debao/db-goods-saved.png"
		},
		{
			"name":"zb-title_png",
			"type":"image",
			"url":"zebra/zb-title.png"
		},
		{
			"name":"zb-borad_jpg",
			"type":"image",
			"url":"zebra/zb-borad.jpg"
		},
		{
			"name":"zb-color-bg0_png",
			"type":"image",
			"url":"zebra/zb-color-bg0.png"
		},
		{
			"name":"zb-color-bg1_png",
			"type":"image",
			"url":"zebra/zb-color-bg1.png"
		},
		{
			"name":"zb-lock_png",
			"type":"image",
			"url":"zebra/zb-lock.png"
		},
		{
			"name":"zb-lock-bg_png",
			"type":"image",
			"url":"zebra/zb-lock-bg.png"
		},
		{
			"name":"zb-pick-bg_jpg",
			"type":"image",
			"url":"zebra/zb-pick-bg.jpg"
		},
		{
			"name":"zb-color-tip_png",
			"type":"image",
			"url":"zebra/zb-color-tip.png"
		},
		{
			"name":"zb-meng4c_png",
			"type":"image",
			"url":"zebra/zb-meng4c.png"
		},
		{
			"name":"zb-meng4g_png",
			"type":"image",
			"url":"zebra/zb-meng4g.png"
		},
		{
			"name":"zb-meng1c_png",
			"type":"image",
			"url":"zebra/zb-meng1c.png"
		},
		{
			"name":"zb-meng1g_png",
			"type":"image",
			"url":"zebra/zb-meng1g.png"
		},
		{
			"name":"zb-meng2c_png",
			"type":"image",
			"url":"zebra/zb-meng2c.png"
		},
		{
			"name":"zb-meng2g_png",
			"type":"image",
			"url":"zebra/zb-meng2g.png"
		},
		{
			"name":"zb-meng3c_png",
			"type":"image",
			"url":"zebra/zb-meng3c.png"
		},
		{
			"name":"zb-meng3g_png",
			"type":"image",
			"url":"zebra/zb-meng3g.png"
		},
		{
			"name":"zb-finish-pop_png",
			"type":"image",
			"url":"zebra/zb-finish-pop.png"
		},
		{
			"name":"zb-pingtu-bg_jpg",
			"type":"image",
			"url":"zebra/zb-pingtu-bg.jpg"
		},
		{
			"name":"zb-pingtu-jia_png",
			"type":"image",
			"url":"zebra/zb-pingtu-jia.png"
		},
		{
			"name":"zb-pingtu-click_png",
			"type":"image",
			"url":"zebra/zb-pingtu-click.png"
		},
		{
			"name":"zb-pingtu-next_png",
			"type":"image",
			"url":"zebra/zb-pingtu-next.png"
		},
		{
			"name":"zb-pingtu-over_png",
			"type":"image",
			"url":"zebra/zb-pingtu-over.png"
		},
		{
			"name":"zb-pingtu-save_png",
			"type":"image",
			"url":"zebra/zb-pingtu-save.png"
		},
		{
			"name":"wk-bian-hand_png",
			"type":"image",
			"url":"wukong/wk-bian-hand.png"
		},
		{
			"name":"wk-bian-tip_png",
			"type":"image",
			"url":"wukong/wk-bian-tip.png"
		},
		{
			"name":"wk-6_jpg",
			"type":"image",
			"url":"wukong/wk-6.jpg"
		},
		{
			"name":"wk-53_png",
			"type":"image",
			"url":"wukong/wk-53.png"
		},
		{
			"name":"wk-52_png",
			"type":"image",
			"url":"wukong/wk-52.png"
		},
		{
			"name":"wk-51_png",
			"type":"image",
			"url":"wukong/wk-51.png"
		},
		{
			"name":"wk-4_jpg",
			"type":"image",
			"url":"wukong/wk-4.jpg"
		},
		{
			"name":"wk-341_png",
			"type":"image",
			"url":"wukong/wk-341.png"
		},
		{
			"name":"wk-340_png",
			"type":"image",
			"url":"wukong/wk-340.png"
		},
		{
			"name":"wk-33_png",
			"type":"image",
			"url":"wukong/wk-33.png"
		},
		{
			"name":"wk-32_png",
			"type":"image",
			"url":"wukong/wk-32.png"
		},
		{
			"name":"wk-31_png",
			"type":"image",
			"url":"wukong/wk-31.png"
		},
		{
			"name":"wk-23_png",
			"type":"image",
			"url":"wukong/wk-23.png"
		},
		{
			"name":"wk-22_png",
			"type":"image",
			"url":"wukong/wk-22.png"
		},
		{
			"name":"wk-21_png",
			"type":"image",
			"url":"wukong/wk-21.png"
		},
		{
			"name":"wk-1_jpg",
			"type":"image",
			"url":"wukong/wk-1.jpg"
		},
		{
			"name":"wk-1next_png",
			"type":"image",
			"url":"wukong/wk-1next.png"
		},
		{
			"name":"wk-chart_png",
			"type":"image",
			"url":"wukong/wk-chart.png"
		}
	]
}